README.md
setup.py
okx_exchange_api/__init__.py
okx_exchange_api/account_api.py
okx_exchange_api/client.py
okx_exchange_api/consts.py
okx_exchange_api/ett_api.py
okx_exchange_api/exceptions.py
okx_exchange_api/futures_api.py
okx_exchange_api/lever_api.py
okx_exchange_api/spot_api.py
okx_exchange_api/swap_api.py
okx_exchange_api/utils.py
okx_exchange_api/websocket.py
okx_exchange_api.egg-info/PKG-INFO
okx_exchange_api.egg-info/SOURCES.txt
okx_exchange_api.egg-info/dependency_links.txt
okx_exchange_api.egg-info/requires.txt
okx_exchange_api.egg-info/top_level.txt