Metadata-Version: 2.1
Name: okx-exchange-api
Version: 1.0.3
Summary: okx交易所api封装
Home-page: https://github.com/AbsoluteValentine/okx-exchange-api
Author: AbsoluteValentine
Author-email: spikeqiang@gamil.com
License: Apache 2.0
Keywords: okx-exchange-api
Classifier: Development Status :: 3 - Alpha
Classifier: Intended Audience :: Developers
Classifier: Programming Language :: Python :: 3
Classifier: Programming Language :: Python :: 3.7
Classifier: Programming Language :: Python :: 3.8
Classifier: Programming Language :: Python :: 3.9
Classifier: Programming Language :: Python :: 3.10
Classifier: Programming Language :: Python :: 3.11
Classifier: Programming Language :: Python :: 3 :: Only
Classifier: License :: OSI Approved :: MIT License
Classifier: Operating System :: OS Independent
Requires-Python: >=3.6
